mcp_think_tool-0.1.0.dist-info/licenses/LICENSE
think_tool/__init__.py
think_tool/server.py
mcp_think_tool-0.1.0.dist-info/METADATA
mcp_think_tool-0.1.0.dist-info/WHEEL
mcp_think_tool-0.1.0.dist-info/entry_points.txt
mcp_think_tool-0.1.0.dist-info/top_level.txt
mcp_think_tool-0.1.0.dist-info/RECORD
